odoo/addons/connector_equipment_import_cdr/README.rst
odoo/addons/connector_equipment_import_cdr/__init__.py
odoo/addons/connector_equipment_import_cdr/__manifest__.py
odoo/addons/connector_equipment_import_cdr/data/backend_equipment_cron.xml
odoo/addons/connector_equipment_import_cdr/data/product_data.xml
odoo/addons/connector_equipment_import_cdr/demo/backend_equipment_productline_demo.xml
odoo/addons/connector_equipment_import_cdr/i18n/connector_equipment_import_cdr.pot
odoo/addons/connector_equipment_import_cdr/models/__init__.py
odoo/addons/connector_equipment_import_cdr/models/agreement_serviceprofile.py
odoo/addons/connector_equipment_import_cdr/models/backend_equipment.py
odoo/addons/connector_equipment_import_cdr/models/backend_equipment_productline.py
odoo/addons/connector_equipment_import_cdr/readme/CONTRIBUTORS.rst
odoo/addons/connector_equipment_import_cdr/readme/DESCRIPTION.rst
odoo/addons/connector_equipment_import_cdr/security/ir.model.access.csv
odoo/addons/connector_equipment_import_cdr/static/description/icon.png
odoo/addons/connector_equipment_import_cdr/static/description/index.html
odoo/addons/connector_equipment_import_cdr/views/agreement_serviceprofile.xml
odoo/addons/connector_equipment_import_cdr/views/backend_equipment_productline.xml
odoo/addons/connector_equipment_import_cdr/views/backend_view.xml
odoo12_addon_connector_equipment_import_cdr-12.0.1.0.0.99.dev20.dist-info/METADATA
odoo12_addon_connector_equipment_import_cdr-12.0.1.0.0.99.dev20.dist-info/WHEEL
odoo12_addon_connector_equipment_import_cdr-12.0.1.0.0.99.dev20.dist-info/top_level.txt
odoo12_addon_connector_equipment_import_cdr-12.0.1.0.0.99.dev20.dist-info/RECORD
